spapros/__init__.py
spapros/__main__.py
spapros/cli/__init__.py
spapros/cli/questionary.py
spapros/evaluation/__init__.py
spapros/evaluation/evaluation.py
spapros/evaluation/evaluation_pipeline.py
spapros/evaluation/metrics.py
spapros/plotting/__init__.py
spapros/plotting/_masked_dotplot.py
spapros/plotting/plot.py
spapros/py.typed
spapros/selection/__init__.py
spapros/selection/selection.py
spapros/selection/selection_methods.py
spapros/selection/selection_procedure.py
spapros/util/__init__.py
spapros/util/mp_util.py
spapros/util/util.py
spapros-0.1.6.dist-info/METADATA
spapros-0.1.6.dist-info/WHEEL
spapros-0.1.6.dist-info/entry_points.txt
spapros-0.1.6.dist-info/licenses/LICENSE
spapros-0.1.6.dist-info/RECORD
