Metadata-Version: 2.4
Name: spapros
Version: 0.1.6
Summary: Probe set selection for targeted spatial transcriptomics.
License: MIT
License-File: LICENSE
Author: Lukas Heumos
Author-email: lukas.heumos@posteo.net
Requires-Python: >=3.11,<3.14
Classifier: License :: OSI Approved :: MIT License
Classifier: Programming Language :: Python :: 3
Classifier: Programming Language :: Python :: 3.11
Classifier: Programming Language :: Python :: 3.12
Classifier: Programming Language :: Python :: 3.13
Requires-Dist: Jinja2 (>=3.0.1)
Requires-Dist: Pillow (>=10.0.2)
Requires-Dist: PyYAML (>=6.0.1)
Requires-Dist: UpSetPlot (>=0.7.0)
Requires-Dist: bandit (>=1.7.6)
Requires-Dist: click (>=8.0.1)
Requires-Dist: jupyter-sphinx (>=0.3.2)
Requires-Dist: leidenalg (>=0.8.7)
Requires-Dist: matplotlib (>=3.6.3)
Requires-Dist: nox (>=2023.04.22)
Requires-Dist: nox-poetry (>=1.0.3)
Requires-Dist: numpy (>=1.21.1)
Requires-Dist: pandas (>=2.0.0,<3.0.0)
Requires-Dist: pandoc (>=2.1)
Requires-Dist: pypi-latest (>=0.1.0)
Requires-Dist: questionary (>=1.10.0)
Requires-Dist: rich (>=10.1.0)
Requires-Dist: ruamel.yaml (>=0.17.10)
Requires-Dist: scanpy (>=1.9.8)
Requires-Dist: seaborn (>=0.11.1)
Requires-Dist: venndata (>=0.1.0)
Requires-Dist: xgboost (>=1.6.1)
Project-URL: Documentation, https://spapros.readthedocs.io
Project-URL: Homepage, https://github.com/theislab/spapros
Project-URL: Repository, https://github.com/theislab/spapros
